{
    "id": "container-env",
    "name": "Container Environment",
    "values": [
        {
            "key": "host",
            "value": "nginx",
            "enabled": true
        },
        {
            "key": "port",
            "value": "80",
            "enabled": true
        },
        {
            "key": "baseUrl",
            "value": "http://nginx:80",
            "enabled": true
        },
        {
            "key": "auth_token",
            "value": "",
            "enabled": true
        }
    ]
} 